{"v":"5.4.4","fr":24,"ip":0,"op":96,"w":996,"h":428,"nm":"cancelpolicy 2","ddd":0,"assets":[],"layers":[{"ddd":0,"ind":1,"ty":4,"nm":"Layer 4","sr":1,"ks":{"o":{"a":0,"k":100,"ix":11},"r":{"a":1,"k":[{"i":{"x":[0.667],"y":[1]},"o":{"x":[0.333],"y":[0]},"t":0,"s":[0],"e":[-4]},{"i":{"x":[0.667],"y":[1]},"o":{"x":[0.333],"y":[0]},"t":34,"s":[-4],"e":[0]},{"t":96}],"ix":10},"p":{"a":1,"k":[{"i":{"x":0.667,"y":1},"o":{"x":0.333,"y":0},"t":0,"s":[709.679,223.386,0],"e":[705.679,221.886,0],"to":[-0.667,-0.25,0],"ti":[0,0,0]},{"i":{"x":0.667,"y":1},"o":{"x":0.333,"y":0},"t":34,"s":[705.679,221.886,0],"e":[709.679,223.386,0],"to":[0,0,0],"ti":[-0.667,-0.25,0]},{"t":96}],"ix":2},"a":{"a":0,"k":[43.256,53.132,0],"ix":1},"s":{"a":0,"k":[100,100,100],"ix":6}},"ao":0,"shapes":[{"ty":"gr","it":[{"ind":0,"ty":"sh","ix":1,"ks":{"a":0,"k":{"i":[[0.795,-10.595],[1.075,-5.094],[-10.22,-13.848],[-5.396,-5.42],[7.222,-1.016],[-16.545,-11.318],[-4.675,4.225],[40.389,11.159],[12.586,2.528]],"o":[[0,0],[-1.076,5.093],[0,0],[5.869,5.895],[0,0],[8.899,6.089],[12.851,-11.612],[-12.074,-3.337],[-7.769,-1.559]],"v":[[-38.497,-31.256],[-28.669,-20.152],[-36.353,14.307],[-25.978,10.623],[-32.879,29.635],[-18.971,47.016],[3.455,44.393],[6.184,-33.479],[-20.522,-51.547]],"c":true},"ix":2},"nm":"Path 1","mn":"ADBE Vector Shape - Group","hd":false},{"ty":"fl","c":{"a":0,"k":[0.255000005984,0.204000001795,0.180000005984,1],"ix":4},"o":{"a":0,"k":100,"ix":5},"r":1,"bm":0,"nm":"Fill 1","mn":"ADBE Vector Graphic - Fill","hd":false},{"ty":"tr","p":{"a":0,"k":[54.796,53.356],"ix":2},"a":{"a":0,"k":[0,0],"ix":1},"s":{"a":0,"k":[100,100],"ix":3},"r":{"a":0,"k":0,"ix":6},"o":{"a":0,"k":100,"ix":7},"sk":{"a":0,"k":0,"ix":4},"sa":{"a":0,"k":0,"ix":5},"nm":"Transform"}],"nm":"Group 1","np":2,"cix":2,"bm":0,"ix":1,"mn":"ADBE Vector Group","hd":false},{"ty":"gr","it":[{"ind":0,"ty":"sh","ix":1,"ks":{"a":0,"k":{"i":[[-0.951,1.722],[-15.202,-5.925],[9.175,-23.506],[-8.056,-8.279],[13.744,5.35],[-9.174,23.506]],"o":[[10.157,-17.917],[16.609,6.498],[-1.578,4.029],[-11.466,16.618],[-16.611,-6.471],[0.714,-1.833]],"v":[[-23.997,-30.687],[19.063,-37.643],[22.884,6.356],[25.809,29.96],[-12.507,43.253],[-26.497,-25.348]],"c":true},"ix":2},"nm":"Path 1","mn":"ADBE Vector Shape - Group","hd":false},{"ty":"fl","c":{"a":0,"k":[0.976000019148,0.728999956916,0.541000007181,1],"ix":4},"o":{"a":0,"k":100,"ix":5},"r":1,"bm":0,"nm":"Fill 1","mn":"ADBE Vector Graphic - Fill","hd":false},{"ty":"tr","p":{"a":0,"k":[35.921,58.711],"ix":2},"a":{"a":0,"k":[0,0],"ix":1},"s":{"a":0,"k":[100,100],"ix":3},"r":{"a":0,"k":0,"ix":6},"o":{"a":0,"k":100,"ix":7},"sk":{"a":0,"k":0,"ix":4},"sa":{"a":0,"k":0,"ix":5},"nm":"Transform"}],"nm":"Group 2","np":2,"cix":2,"bm":0,"ix":2,"mn":"ADBE Vector Group","hd":false}],"ip":0,"op":144,"st":0,"bm":0},{"ddd":0,"ind":2,"ty":4,"nm":"Layer 3","sr":1,"ks":{"o":{"a":0,"k":100,"ix":11},"r":{"a":1,"k":[{"i":{"x":[0.667],"y":[0.75]},"o":{"x":[0.333],"y":[0]},"t":0,"s":[0],"e":[-1]},{"i":{"x":[0.667],"y":[1]},"o":{"x":[0.333],"y":[-0.25]},"t":17,"s":[-1],"e":[-1]},{"i":{"x":[0.833],"y":[1]},"o":{"x":[0.333],"y":[0]},"t":34,"s":[-1],"e":[10]},{"i":{"x":[0.667],"y":[1]},"o":{"x":[0.167],"y":[0]},"t":58,"s":[10],"e":[0]},{"t":96}],"ix":10},"p":{"a":1,"k":[{"i":{"x":0.667,"y":0.59},"o":{"x":0.333,"y":0},"t":0,"s":[636.871,353.759,0],"e":[635.621,355.509,0],"to":[-0.208,0.208,0],"ti":[0.521,-0.521,0]},{"i":{"x":0.667,"y":1},"o":{"x":0.333,"y":0.602},"t":17,"s":[635.621,355.509,0],"e":[634.371,356.259,0],"to":[-0.521,0.521,0],"ti":[0.208,-0.208,0]},{"i":{"x":0.667,"y":1},"o":{"x":0.333,"y":0},"t":34,"s":[634.371,356.259,0],"e":[626.871,351.259,0],"to":[-0.417,0.417,0],"ti":[0,0,0]},{"i":{"x":0.667,"y":1},"o":{"x":0.333,"y":0},"t":58,"s":[626.871,351.259,0],"e":[636.871,353.759,0],"to":[0,0,0],"ti":[0.417,-0.417,0]},{"t":96}],"ix":2},"a":{"a":0,"k":[48.02,62.737,0],"ix":1},"s":{"a":1,"k":[{"i":{"x":[0.667,0.667,0.667],"y":[1,1,1]},"o":{"x":[0.333,0.333,0.333],"y":[0,0,0]},"t":0,"s":[100,100,100],"e":[102,100,100]},{"i":{"x":[0.833,0.833,0.833],"y":[1,1,1]},"o":{"x":[0.333,0.333,0.333],"y":[0,0,0]},"t":34,"s":[102,100,100],"e":[96,100,100]},{"i":{"x":[0.667,0.667,0.667],"y":[1,1,1]},"o":{"x":[0.167,0.167,0.167],"y":[0,0,0]},"t":58,"s":[96,100,100],"e":[100,100,100]},{"t":96}],"ix":6}},"ao":0,"shapes":[{"ty":"gr","it":[{"ind":0,"ty":"sh","ix":1,"ks":{"a":0,"k":{"i":[[0,0],[0,0],[16.702,-18.187],[8.064,-12.279],[-10.597,-1.295],[-12.024,7.601]],"o":[[0,0],[0,0],[-10.848,11.813],[-17.173,26.147],[7.409,0.905],[0,0]],"v":[[45.63,11.561],[41.683,-62.876],[11.104,-38.262],[-25.916,14.132],[-35.033,61.971],[-7.172,51.244]],"c":true},"ix":2},"nm":"Path 1","mn":"ADBE Vector Shape - Group","hd":false},{"ty":"fl","c":{"a":0,"k":[0,0.694000004787,0.310000011968,1],"ix":4},"o":{"a":0,"k":100,"ix":5},"r":1,"bm":0,"nm":"Fill 1","mn":"ADBE Vector Graphic - Fill","hd":false},{"ty":"tr","p":{"a":0,"k":[45.88,63.126],"ix":2},"a":{"a":0,"k":[0,0],"ix":1},"s":{"a":0,"k":[100,100],"ix":3},"r":{"a":0,"k":0,"ix":6},"o":{"a":0,"k":100,"ix":7},"sk":{"a":0,"k":0,"ix":4},"sa":{"a":0,"k":0,"ix":5},"nm":"Transform"}],"nm":"Group 1","np":4,"cix":2,"bm":0,"ix":1,"mn":"ADBE Vector Group","hd":false}],"ip":0,"op":144,"st":0,"bm":0},{"ddd":0,"ind":3,"ty":4,"nm":"Layer 2","sr":1,"ks":{"o":{"a":0,"k":100,"ix":11},"r":{"a":1,"k":[{"i":{"x":[0.667],"y":[1]},"o":{"x":[0.333],"y":[0]},"t":0,"s":[0],"e":[-8]},{"i":{"x":[0.667],"y":[1]},"o":{"x":[0.333],"y":[0]},"t":34,"s":[-8],"e":[0]},{"t":96}],"ix":10},"p":{"a":1,"k":[{"i":{"x":0.667,"y":1},"o":{"x":0.333,"y":0},"t":0,"s":[499.577,259.773,0],"e":[480.077,278.773,0],"to":[-3.25,3.167,0],"ti":[4.583,-0.333,0]},{"i":{"x":0.667,"y":1},"o":{"x":0.333,"y":0},"t":34,"s":[480.077,278.773,0],"e":[472.077,261.773,0],"to":[-4.583,0.333,0],"ti":[-3.25,3.167,0]},{"i":{"x":0.667,"y":1},"o":{"x":0.333,"y":0},"t":58,"s":[472.077,261.773,0],"e":[499.577,259.773,0],"to":[3.25,-3.167,0],"ti":[-4.583,0.333,0]},{"t":96}],"ix":2},"a":{"a":0,"k":[145.564,167.964,0],"ix":1},"s":{"a":0,"k":[100,100,100],"ix":6}},"ao":0,"shapes":[{"ty":"gr","it":[{"ind":0,"ty":"sh","ix":1,"ks":{"a":0,"k":{"i":[[0,0],[0,0],[0,0]],"o":[[0,0],[0,0],[0,0]],"v":[[18.151,18.559],[-18.151,-26.705],[10.781,26.705]],"c":true},"ix":2},"nm":"Path 1","mn":"ADBE Vector Shape - Group","hd":false},{"ty":"fl","c":{"a":0,"k":[0,0.556999954523,0.246999987434,1],"ix":4},"o":{"a":0,"k":100,"ix":5},"r":1,"bm":0,"nm":"Fill 1","mn":"ADBE Vector Graphic - Fill","hd":false},{"ty":"tr","p":{"a":0,"k":[242.866,265.132],"ix":2},"a":{"a":0,"k":[0,0],"ix":1},"s":{"a":0,"k":[100,100],"ix":3},"r":{"a":0,"k":0,"ix":6},"o":{"a":0,"k":100,"ix":7},"sk":{"a":0,"k":0,"ix":4},"sa":{"a":0,"k":0,"ix":5},"nm":"Transform"}],"nm":"Group 1","np":4,"cix":2,"bm":0,"ix":1,"mn":"ADBE Vector Group","hd":false},{"ty":"gr","it":[{"ind":0,"ty":"sh","ix":1,"ks":{"a":0,"k":{"i":[[0,0],[0,0],[0,0],[-7.176,-15.347],[-10.598,-1.295],[-12.023,7.601]],"o":[[0,0],[0,0],[0,0],[2.833,6.058],[7.408,0.905],[0,0]],"v":[[12.923,-1.37],[-23.459,-47.375],[-31.666,-37.326],[-16.134,28.638],[3.807,46.471],[31.666,35.743]],"c":true},"ix":2},"nm":"Path 1","mn":"ADBE Vector Shape - Group","hd":false},{"ty":"fl","c":{"a":0,"k":[0,0.694000004787,0.310000011968,1],"ix":4},"o":{"a":0,"k":100,"ix":5},"r":1,"bm":0,"nm":"Fill 1","mn":"ADBE Vector Graphic - Fill","hd":false},{"ty":"tr","p":{"a":0,"k":[241.878,277.841],"ix":2},"a":{"a":0,"k":[0,0],"ix":1},"s":{"a":0,"k":[100,100],"ix":3},"r":{"a":0,"k":0,"ix":6},"o":{"a":0,"k":100,"ix":7},"sk":{"a":0,"k":0,"ix":4},"sa":{"a":0,"k":0,"ix":5},"nm":"Transform"}],"nm":"Group 2","np":4,"cix":2,"bm":0,"ix":2,"mn":"ADBE Vector Group","hd":false},{"ty":"gr","it":[{"ind":0,"ty":"sh","ix":1,"ks":{"a":0,"k":{"i":[[0,0],[0.737,-0.126],[-0.185,-1.031],[-0.032,-0.091],[-1.505,-4.401],[0,0],[0.997,-0.81],[0.124,-0.179],[-0.271,-0.713],[-12.904,-5.711],[0,0],[0,0],[0,0]],"o":[[-0.423,-0.617],[-1.031,0.184],[0.017,0.095],[0,0],[-5.065,1.373],[-0.811,-0.998],[-0.17,0.138],[-0.441,0.623],[2.061,5.469],[0,0],[0,0],[0,0],[0,0]],"v":[[3.426,-9.714],[1.523,-10.52],[-0.009,-8.32],[0.064,-8.04],[3.54,2.052],[-12.93,-18.471],[-16.203,-18.812],[-16.647,-18.334],[-16.918,-16.197],[7.554,18.455],[8.982,19.621],[17.189,9.572],[15.599,8.272]],"c":true},"ix":2},"nm":"Path 1","mn":"ADBE Vector Shape - Group","hd":false},{"ty":"fl","c":{"a":0,"k":[0.976000019148,0.728999956916,0.541000007181,1],"ix":4},"o":{"a":0,"k":100,"ix":5},"r":1,"bm":0,"nm":"Fill 1","mn":"ADBE Vector Graphic - Fill","hd":false},{"ty":"tr","p":{"a":0,"k":[201.23,220.893],"ix":2},"a":{"a":0,"k":[0,0],"ix":1},"s":{"a":0,"k":[100,100],"ix":3},"r":{"a":0,"k":0,"ix":6},"o":{"a":0,"k":100,"ix":7},"sk":{"a":0,"k":0,"ix":4},"sa":{"a":0,"k":0,"ix":5},"nm":"Transform"}],"nm":"Group 3","np":4,"cix":2,"bm":0,"ix":3,"mn":"ADBE Vector Group","hd":false},{"ty":"gr","it":[{"ind":0,"ty":"sh","ix":1,"ks":{"a":0,"k":{"i":[[0.52,0],[0.397,0.397],[0,0],[-0.793,0.793],[-0.793,-0.793],[0,0],[0.793,-0.793]],"o":[[-0.52,0],[0,0],[-0.793,-0.793],[0.793,-0.793],[0,0],[0.793,0.793],[-0.396,0.397]],"v":[[4.526,6.656],[3.09,6.061],[-5.962,-2.991],[-5.962,-5.863],[-3.091,-5.863],[5.962,3.19],[5.962,6.061]],"c":true},"ix":2},"nm":"Path 1","mn":"ADBE Vector Shape - Group","hd":false},{"ty":"fl","c":{"a":0,"k":[1,1,1,1],"ix":4},"o":{"a":0,"k":100,"ix":5},"r":1,"bm":0,"nm":"Fill 1","mn":"ADBE Vector Graphic - Fill","hd":false},{"ty":"tr","p":{"a":0,"k":[180.825,183.948],"ix":2},"a":{"a":0,"k":[0,0],"ix":1},"s":{"a":0,"k":[100,100],"ix":3},"r":{"a":0,"k":0,"ix":6},"o":{"a":0,"k":100,"ix":7},"sk":{"a":0,"k":0,"ix":4},"sa":{"a":0,"k":0,"ix":5},"nm":"Transform"}],"nm":"Group 4","np":4,"cix":2,"bm":0,"ix":4,"mn":"ADBE Vector Group","hd":false},{"ty":"gr","it":[{"ind":0,"ty":"sh","ix":1,"ks":{"a":0,"k":{"i":[[0,0],[0,0],[0,0]],"o":[[0,0],[0,0],[0,0]],"v":[[14.523,7.589],[-2.286,-7.589],[-14.523,4.647]],"c":true},"ix":2},"nm":"Path 1","mn":"ADBE Vector Shape - Group","hd":false},{"ty":"fl","c":{"a":0,"k":[0.685999971278,0.685999971278,0.689999988032,1],"ix":4},"o":{"a":0,"k":100,"ix":5},"r":1,"bm":0,"nm":"Fill 1","mn":"ADBE Vector Graphic - Fill","hd":false},{"ty":"tr","p":{"a":0,"k":[177.764,174.048],"ix":2},"a":{"a":0,"k":[0,0],"ix":1},"s":{"a":0,"k":[100,100],"ix":3},"r":{"a":0,"k":0,"ix":6},"o":{"a":0,"k":100,"ix":7},"sk":{"a":0,"k":0,"ix":4},"sa":{"a":0,"k":0,"ix":5},"nm":"Transform"}],"nm":"Group 5","np":4,"cix":2,"bm":0,"ix":5,"mn":"ADBE Vector Group","hd":false},{"ty":"gr","it":[{"ind":0,"ty":"sh","ix":1,"ks":{"a":0,"k":{"i":[[-0.968,-3.388],[3.387,-0.969],[0.969,3.388],[-3.387,0.968]],"o":[[0.969,3.387],[-3.388,0.968],[-0.968,-3.387],[3.387,-0.969]],"v":[[6.133,-1.753],[1.754,6.134],[-6.134,1.754],[-1.754,-6.133]],"c":true},"ix":2},"nm":"Path 1","mn":"ADBE Vector Shape - Group","hd":false},{"ty":"fl","c":{"a":0,"k":[1,1,1,1],"ix":4},"o":{"a":0,"k":100,"ix":5},"r":1,"bm":0,"nm":"Fill 1","mn":"ADBE Vector Graphic - Fill","hd":false},{"ty":"tr","p":{"a":0,"k":[67.542,44.695],"ix":2},"a":{"a":0,"k":[0,0],"ix":1},"s":{"a":0,"k":[100,100],"ix":3},"r":{"a":0,"k":0,"ix":6},"o":{"a":0,"k":100,"ix":7},"sk":{"a":0,"k":0,"ix":4},"sa":{"a":0,"k":0,"ix":5},"nm":"Transform"}],"nm":"Group 6","np":4,"cix":2,"bm":0,"ix":6,"mn":"ADBE Vector Group","hd":false},{"ty":"gr","it":[{"ind":0,"ty":"sh","ix":1,"ks":{"a":0,"k":{"i":[[0.569,0],[0.771,2.489],[33.308,-10.333],[0.95,3.06],[-3.062,0.95],[-12.231,-39.415],[3.062,-0.949]],"o":[[-2.475,0],[-10.333,-33.301],[-3.054,0.95],[-0.95,-3.062],[39.407,-12.231],[0.95,3.061],[-0.571,0.178]],"v":[[43.199,34.528],[37.658,30.443],[-41.48,-11.211],[-48.742,-15.034],[-44.919,-22.297],[48.742,27.003],[44.919,34.265]],"c":true},"ix":2},"nm":"Path 1","mn":"ADBE Vector Shape - Group","hd":false},{"ty":"fl","c":{"a":0,"k":[1,1,1,1],"ix":4},"o":{"a":0,"k":100,"ix":5},"r":1,"bm":0,"nm":"Fill 1","mn":"ADBE Vector Graphic - Fill","hd":false},{"ty":"tr","p":{"a":0,"k":[126.231,56.229],"ix":2},"a":{"a":0,"k":[0,0],"ix":1},"s":{"a":0,"k":[100,100],"ix":3},"r":{"a":0,"k":0,"ix":6},"o":{"a":0,"k":100,"ix":7},"sk":{"a":0,"k":0,"ix":4},"sa":{"a":0,"k":0,"ix":5},"nm":"Transform"}],"nm":"Group 7","np":4,"cix":2,"bm":0,"ix":7,"mn":"ADBE Vector Group","hd":false},{"ty":"gr","it":[{"ind":0,"ty":"sh","ix":1,"ks":{"a":0,"k":{"i":[[25.774,41.396],[41.396,-25.775],[-25.775,-41.396],[-41.396,25.775]],"o":[[-25.775,-41.396],[-41.396,25.775],[25.775,41.395],[41.396,-25.774]],"v":[[75.071,-46.741],[-46.744,-75.073],[-75.071,46.745],[46.742,75.073]],"c":true},"ix":2},"nm":"Path 1","mn":"ADBE Vector Shape - Group","hd":false},{"ind":1,"ty":"sh","ix":2,"ks":{"a":0,"k":{"i":[[26.388,42.38],[-42.38,26.388],[-26.388,-42.38],[42.381,-26.388]],"o":[[-26.387,-42.381],[42.381,-26.387],[26.387,42.381],[-42.38,26.387]],"v":[[-76.856,47.856],[-47.856,-76.857],[76.856,-47.852],[47.853,76.858]],"c":true},"ix":2},"nm":"Path 2","mn":"ADBE Vector Shape - Group","hd":false},{"ty":"mm","mm":1,"nm":"Merge Paths 1","mn":"ADBE Vector Filter - Merge","hd":false},{"ty":"fl","c":{"a":0,"k":[1,1,1,1],"ix":4},"o":{"a":0,"k":100,"ix":5},"r":1,"bm":0,"nm":"Fill 1","mn":"ADBE Vector Graphic - Fill","hd":false},{"ty":"tr","p":{"a":0,"k":[103.493,105.414],"ix":2},"a":{"a":0,"k":[0,0],"ix":1},"s":{"a":0,"k":[100,100],"ix":3},"r":{"a":0,"k":0,"ix":6},"o":{"a":0,"k":100,"ix":7},"sk":{"a":0,"k":0,"ix":4},"sa":{"a":0,"k":0,"ix":5},"nm":"Transform"}],"nm":"Group 8","np":6,"cix":2,"bm":0,"ix":8,"mn":"ADBE Vector Group","hd":false},{"ty":"gr","it":[{"ind":0,"ty":"sh","ix":1,"ks":{"a":0,"k":{"i":[[8.418,0],[11.56,39.161],[-47.636,14.058],[0,0],[-14.002,-47.447],[-47.442,13.997],[0,0]],"o":[[-38.903,0.002],[-14.057,-47.639],[0,0],[-47.444,14.003],[14,47.445],[0,0],[-8.475,2.502]],"v":[[37.52,83.261],[-48.917,18.674],[11.978,-93.218],[12.082,-92.872],[-48.567,18.571],[62.871,79.221],[62.974,79.568]],"c":true},"ix":2},"nm":"Path 1","mn":"ADBE Vector Shape - Group","hd":false},{"ty":"fl","c":{"a":0,"k":[1,1,1,1],"ix":4},"o":{"a":0,"k":100,"ix":5},"r":1,"bm":0,"nm":"Fill 1","mn":"ADBE Vector Graphic - Fill","hd":false},{"ty":"tr","p":{"a":0,"k":[73.466,110.109],"ix":2},"a":{"a":0,"k":[0,0],"ix":1},"s":{"a":0,"k":[100,100],"ix":3},"r":{"a":0,"k":0,"ix":6},"o":{"a":0,"k":100,"ix":7},"sk":{"a":0,"k":0,"ix":4},"sa":{"a":0,"k":0,"ix":5},"nm":"Transform"}],"nm":"Group 9","np":4,"cix":2,"bm":0,"ix":9,"mn":"ADBE Vector Group","hd":false},{"ty":"gr","it":[{"ind":0,"ty":"sh","ix":1,"ks":{"a":0,"k":{"i":[[20.25,32.521],[-42.079,26.201],[-5.288,2.022],[9.558,-5.951],[-26.2,-42.079],[-39.379,15.056]],"o":[[-26.2,-42.08],[4.982,-3.102],[-10.445,2.031],[-42.079,26.201],[23.099,37.098],[-35.542,6.912]],"v":[[-26.276,37.87],[2.517,-85.958],[17.962,-93.618],[-12.296,-81.723],[-41.09,42.106],[67.289,78.562]],"c":true},"ix":2},"nm":"Path 1","mn":"ADBE Vector Shape - Group","hd":false},{"ty":"fl","c":{"a":0,"k":[0.6,0.859000052658,0.922000002394,1],"ix":4},"o":{"a":0,"k":100,"ix":5},"r":1,"bm":0,"nm":"Fill 1","mn":"ADBE Vector Graphic - Fill","hd":false},{"ty":"tr","p":{"a":0,"k":[68.271,110.825],"ix":2},"a":{"a":0,"k":[0,0],"ix":1},"s":{"a":0,"k":[100,100],"ix":3},"r":{"a":0,"k":0,"ix":6},"o":{"a":0,"k":100,"ix":7},"sk":{"a":0,"k":0,"ix":4},"sa":{"a":0,"k":0,"ix":5},"nm":"Transform"}],"nm":"Group 10","np":4,"cix":2,"bm":0,"ix":10,"mn":"ADBE Vector Group","hd":false},{"ty":"gr","it":[{"ind":0,"ty":"sh","ix":1,"ks":{"a":0,"k":{"i":[[26.201,42.08],[42.08,-26.201],[-26.2,-42.08],[-42.079,26.2]],"o":[[-26.201,-42.08],[-42.08,26.2],[26.201,42.079],[42.08,-26.201]],"v":[[76.311,-47.513],[-47.517,-76.313],[-76.312,47.516],[47.514,76.313]],"c":true},"ix":2},"nm":"Path 1","mn":"ADBE Vector Shape - Group","hd":false},{"ty":"fl","c":{"a":0,"k":[0.8,0.929000016755,0.961000031116,1],"ix":4},"o":{"a":0,"k":40,"ix":5},"r":1,"bm":0,"nm":"Fill 1","mn":"ADBE Vector Graphic - Fill","hd":false},{"ty":"tr","p":{"a":0,"k":[103.493,105.415],"ix":2},"a":{"a":0,"k":[0,0],"ix":1},"s":{"a":0,"k":[100,100],"ix":3},"r":{"a":0,"k":0,"ix":6},"o":{"a":0,"k":100,"ix":7},"sk":{"a":0,"k":0,"ix":4},"sa":{"a":0,"k":0,"ix":5},"nm":"Transform"}],"nm":"Group 11","np":4,"cix":2,"bm":0,"ix":11,"mn":"ADBE Vector Group","hd":false},{"ty":"gr","it":[{"ind":0,"ty":"sh","ix":1,"ks":{"a":0,"k":{"i":[[-5.107,-3.984],[1.667,-2.137],[5.107,3.984],[-1.667,2.137]],"o":[[5.107,3.984],[-1.667,2.137],[-5.107,-3.985],[1.667,-2.136]],"v":[[3.018,-3.87],[9.247,7.214],[-3.019,3.87],[-9.247,-7.214]],"c":true},"ix":2},"nm":"Path 1","mn":"ADBE Vector Shape - Group","hd":false},{"ty":"fl","c":{"a":0,"k":[0.2,0.757000014361,0.447000002394,1],"ix":4},"o":{"a":0,"k":100,"ix":5},"r":1,"bm":0,"nm":"Fill 1","mn":"ADBE Vector Graphic - Fill","hd":false},{"ty":"tr","p":{"a":0,"k":[251.995,246.764],"ix":2},"a":{"a":0,"k":[0,0],"ix":1},"s":{"a":0,"k":[100,100],"ix":3},"r":{"a":0,"k":0,"ix":6},"o":{"a":0,"k":100,"ix":7},"sk":{"a":0,"k":0,"ix":4},"sa":{"a":0,"k":0,"ix":5},"nm":"Transform"}],"nm":"Group 12","np":4,"cix":2,"bm":0,"ix":12,"mn":"ADBE Vector Group","hd":false},{"ty":"gr","it":[{"ind":0,"ty":"sh","ix":1,"ks":{"a":0,"k":{"i":[[0,0],[0,0],[0,0],[0,0]],"o":[[0,0],[0,0],[0,0],[0,0]],"v":[[-5.366,9.788],[9.781,-5.386],[4.908,-9.788],[-9.781,4.9]],"c":true},"ix":2},"nm":"Path 1","mn":"ADBE Vector Shape - Group","hd":false},{"ty":"fl","c":{"a":0,"k":[0,0.416000007181,0.184000007779,1],"ix":4},"o":{"a":0,"k":100,"ix":5},"r":1,"bm":0,"nm":"Fill 1","mn":"ADBE Vector Graphic - Fill","hd":false},{"ty":"tr","p":{"a":0,"k":[195.132,198.361],"ix":2},"a":{"a":0,"k":[0,0],"ix":1},"s":{"a":0,"k":[100,100],"ix":3},"r":{"a":0,"k":0,"ix":6},"o":{"a":0,"k":100,"ix":7},"sk":{"a":0,"k":0,"ix":4},"sa":{"a":0,"k":0,"ix":5},"nm":"Transform"}],"nm":"Group 13","np":4,"cix":2,"bm":0,"ix":13,"mn":"ADBE Vector Group","hd":false},{"ty":"gr","it":[{"ind":0,"ty":"sh","ix":1,"ks":{"a":0,"k":{"i":[[-11.298,28.258],[6.168,-6.168],[5.95,6.379],[0,0]],"o":[[6.379,5.95],[-6.168,6.168],[0,0],[0,0]],"v":[[40.672,11.543],[41.058,33.714],[18.887,33.328],[-47.226,-39.882]],"c":true},"ix":2},"nm":"Path 1","mn":"ADBE Vector Shape - Group","hd":false},{"ty":"fl","c":{"a":0,"k":[0,0.416000007181,0.184000007779,1],"ix":4},"o":{"a":0,"k":100,"ix":5},"r":1,"bm":0,"nm":"Fill 1","mn":"ADBE Vector Graphic - Fill","hd":false},{"ty":"tr","p":{"a":0,"k":[232.577,243.143],"ix":2},"a":{"a":0,"k":[0,0],"ix":1},"s":{"a":0,"k":[100,100],"ix":3},"r":{"a":0,"k":0,"ix":6},"o":{"a":0,"k":100,"ix":7},"sk":{"a":0,"k":0,"ix":4},"sa":{"a":0,"k":0,"ix":5},"nm":"Transform"}],"nm":"Group 14","np":4,"cix":2,"bm":0,"ix":14,"mn":"ADBE Vector Group","hd":false},{"ty":"gr","it":[{"ind":0,"ty":"sh","ix":1,"ks":{"a":0,"k":{"i":[[0,0],[0,0],[-6.168,6.168],[6.379,5.95],[0,0]],"o":[[0,0],[5.95,6.379],[6.168,-6.168],[0,0],[0,0]],"v":[[-47.226,-32.538],[18.887,40.671],[41.058,41.058],[40.672,18.887],[-32.538,-47.226]],"c":true},"ix":2},"nm":"Path 1","mn":"ADBE Vector Shape - Group","hd":false},{"ty":"fl","c":{"a":0,"k":[0,0.694000004787,0.310000011968,1],"ix":4},"o":{"a":0,"k":100,"ix":5},"r":1,"bm":0,"nm":"Fill 1","mn":"ADBE Vector Graphic - Fill","hd":false},{"ty":"tr","p":{"a":0,"k":[232.577,235.799],"ix":2},"a":{"a":0,"k":[0,0],"ix":1},"s":{"a":0,"k":[100,100],"ix":3},"r":{"a":0,"k":0,"ix":6},"o":{"a":0,"k":100,"ix":7},"sk":{"a":0,"k":0,"ix":4},"sa":{"a":0,"k":0,"ix":5},"nm":"Transform"}],"nm":"Group 15","np":4,"cix":2,"bm":0,"ix":15,"mn":"ADBE Vector Group","hd":false},{"ty":"gr","it":[{"ind":0,"ty":"sh","ix":1,"ks":{"a":0,"k":{"i":[[26.201,42.08],[44.247,-18.51],[-20.249,-32.522],[42.081,-26.2],[5.289,-2.022],[-9.018,6.742]],"o":[[-23.099,-37.098],[35.544,-6.911],[26.201,42.079],[-4.982,3.102],[10.446,-2.032],[32.143,-24.031]],"v":[[41.978,-39.01],[-68.178,-76.058],[34.4,-36.916],[5.603,86.908],[-9.844,94.568],[22.483,79.229]],"c":true},"ix":2},"nm":"Path 1","mn":"ADBE Vector Shape - Group","hd":false},{"ty":"fl","c":{"a":0,"k":[0.842999985639,0.842999985639,0.851000019148,1],"ix":4},"o":{"a":0,"k":100,"ix":5},"r":1,"bm":0,"nm":"Fill 1","mn":"ADBE Vector Graphic - Fill","hd":false},{"ty":"tr","p":{"a":0,"k":[145.404,94.819],"ix":2},"a":{"a":0,"k":[0,0],"ix":1},"s":{"a":0,"k":[100,100],"ix":3},"r":{"a":0,"k":0,"ix":6},"o":{"a":0,"k":100,"ix":7},"sk":{"a":0,"k":0,"ix":4},"sa":{"a":0,"k":0,"ix":5},"nm":"Transform"}],"nm":"Group 16","np":4,"cix":2,"bm":0,"ix":16,"mn":"ADBE Vector Group","hd":false},{"ty":"gr","it":[{"ind":0,"ty":"sh","ix":1,"ks":{"a":0,"k":{"i":[[6.168,-6.168],[0,0],[5.949,6.379],[0,0],[0,0],[0,0]],"o":[[0,0],[-6.168,6.168],[0,0],[0,0],[0,0],[6.379,5.95]],"v":[[52.133,52.132],[52.133,52.132],[29.962,51.746],[-58.301,-45.99],[-45.989,-58.3],[51.746,29.962]],"c":true},"ix":2},"nm":"Path 1","mn":"ADBE Vector Shape - Group","hd":false},{"ty":"fl","c":{"a":0,"k":[0.842999985639,0.842999985639,0.851000019148,1],"ix":4},"o":{"a":0,"k":100,"ix":5},"r":1,"bm":0,"nm":"Fill 1","mn":"ADBE Vector Graphic - Fill","hd":false},{"ty":"tr","p":{"a":0,"k":[221.502,224.724],"ix":2},"a":{"a":0,"k":[0,0],"ix":1},"s":{"a":0,"k":[100,100],"ix":3},"r":{"a":0,"k":0,"ix":6},"o":{"a":0,"k":100,"ix":7},"sk":{"a":0,"k":0,"ix":4},"sa":{"a":0,"k":0,"ix":5},"nm":"Transform"}],"nm":"Group 17","np":4,"cix":2,"bm":0,"ix":17,"mn":"ADBE Vector Group","hd":false}],"ip":0,"op":144,"st":0,"bm":0},{"ddd":0,"ind":4,"ty":4,"nm":"info","sr":1,"ks":{"o":{"a":0,"k":100,"ix":11},"r":{"a":0,"k":0,"ix":10},"p":{"a":0,"k":[497.937,213.632,0],"ix":2},"a":{"a":0,"k":[497.933,214.295,0],"ix":1},"s":{"a":0,"k":[100,100,100],"ix":6}},"ao":0,"shapes":[{"ty":"gr","it":[{"ind":0,"ty":"sh","ix":1,"ks":{"a":0,"k":{"i":[[0,0],[0,0],[0,0]],"o":[[0,0],[0,0],[0,0]],"v":[[-41.964,22.961],[41.964,22.961],[0,-22.961]],"c":true},"ix":2},"nm":"Path 1","mn":"ADBE Vector Shape - Group","hd":false},{"ty":"fl","c":{"a":0,"k":[0.898000021542,0.964999988032,0.929000016755,1],"ix":4},"o":{"a":0,"k":100,"ix":5},"r":1,"bm":0,"nm":"Fill 1","mn":"ADBE Vector Graphic - Fill","hd":false},{"ty":"tr","p":{"a":0,"k":[935.756,166.082],"ix":2},"a":{"a":0,"k":[0,0],"ix":1},"s":{"a":0,"k":[100,100],"ix":3},"r":{"a":0,"k":0,"ix":6},"o":{"a":0,"k":100,"ix":7},"sk":{"a":0,"k":0,"ix":4},"sa":{"a":0,"k":0,"ix":5},"nm":"Transform"}],"nm":"Group 1","np":4,"cix":2,"bm":0,"ix":1,"mn":"ADBE Vector Group","hd":false},{"ty":"gr","it":[{"ind":0,"ty":"sh","ix":1,"ks":{"a":0,"k":{"i":[[-7.57,0],[0,-7.57],[7.569,0],[0,7.569]],"o":[[7.569,0],[0,7.569],[-7.57,0],[0,-7.57]],"v":[[0,-13.707],[13.706,0],[0,13.707],[-13.706,0]],"c":true},"ix":2},"nm":"Path 1","mn":"ADBE Vector Shape - Group","hd":false},{"ty":"fl","c":{"a":0,"k":[0.898000021542,0.964999988032,0.929000016755,1],"ix":4},"o":{"a":0,"k":100,"ix":5},"r":1,"bm":0,"nm":"Fill 1","mn":"ADBE Vector Graphic - Fill","hd":false},{"ty":"tr","p":{"a":0,"k":[917.398,124.427],"ix":2},"a":{"a":0,"k":[0,0],"ix":1},"s":{"a":0,"k":[100,100],"ix":3},"r":{"a":0,"k":0,"ix":6},"o":{"a":0,"k":100,"ix":7},"sk":{"a":0,"k":0,"ix":4},"sa":{"a":0,"k":0,"ix":5},"nm":"Transform"}],"nm":"Group 2","np":4,"cix":2,"bm":0,"ix":2,"mn":"ADBE Vector Group","hd":false},{"ty":"gr","it":[{"ind":0,"ty":"sh","ix":1,"ks":{"a":0,"k":{"i":[[0,0],[0,0],[0,0]],"o":[[0,0],[0,0],[0,0]],"v":[[-51.888,28.392],[51.888,28.392],[0,-28.392]],"c":true},"ix":2},"nm":"Path 1","mn":"ADBE Vector Shape - Group","hd":false},{"ty":"fl","c":{"a":0,"k":[0.898000021542,0.964999988032,0.929000016755,1],"ix":4},"o":{"a":0,"k":100,"ix":5},"r":1,"bm":0,"nm":"Fill 1","mn":"ADBE Vector Graphic - Fill","hd":false},{"ty":"tr","p":{"a":0,"k":[869.426,160.651],"ix":2},"a":{"a":0,"k":[0,0],"ix":1},"s":{"a":0,"k":[100,100],"ix":3},"r":{"a":0,"k":0,"ix":6},"o":{"a":0,"k":100,"ix":7},"sk":{"a":0,"k":0,"ix":4},"sa":{"a":0,"k":0,"ix":5},"nm":"Transform"}],"nm":"Group 3","np":4,"cix":2,"bm":0,"ix":3,"mn":"ADBE Vector Group","hd":false},{"ty":"gr","it":[{"ind":0,"ty":"sh","ix":1,"ks":{"a":0,"k":{"i":[[0,0],[0,0],[0,26.982],[6.538,16.347],[0,0]],"o":[[0,0],[13.031,-21.506],[0,-18.682],[0,0],[0,0]],"v":[[-94.77,63.284],[74.234,63.284],[94.77,-10.431],[84.598,-63.284],[-94.77,-63.284]],"c":true},"ix":2},"nm":"Path 1","mn":"ADBE Vector Shape - Group","hd":false},{"ty":"fl","c":{"a":0,"k":[0.8,0.936999990426,0.859000052658,1],"ix":4},"o":{"a":0,"k":100,"ix":5},"r":1,"bm":0,"nm":"Fill 1","mn":"ADBE Vector Graphic - Fill","hd":false},{"ty":"tr","p":{"a":0,"k":[895.141,153.133],"ix":2},"a":{"a":0,"k":[0,0],"ix":1},"s":{"a":0,"k":[100,100],"ix":3},"r":{"a":0,"k":0,"ix":6},"o":{"a":0,"k":100,"ix":7},"sk":{"a":0,"k":0,"ix":4},"sa":{"a":0,"k":0,"ix":5},"nm":"Transform"}],"nm":"Group 4","np":4,"cix":2,"bm":0,"ix":4,"mn":"ADBE Vector Group","hd":false},{"ty":"gr","it":[{"ind":0,"ty":"sh","ix":1,"ks":{"a":0,"k":{"i":[[0,-5.898],[0,0],[-5.899,0],[0,0],[0,33.571],[10.962,20.182],[0,0]],"o":[[0,0],[0,5.899],[0,0],[19.427,-24.348],[0,-24.582],[0,0],[-5.899,0]],"v":[[-103.097,-67.642],[-103.097,67.642],[-92.416,78.322],[72.03,78.322],[103.097,-10.431],[85.909,-78.322],[-92.416,-78.322]],"c":true},"ix":2},"nm":"Path 1","mn":"ADBE Vector Shape - Group","hd":false},{"ty":"fl","c":{"a":0,"k":[0.6,0.875,0.722000002394,1],"ix":4},"o":{"a":0,"k":100,"ix":5},"r":1,"bm":0,"nm":"Fill 1","mn":"ADBE Vector Graphic - Fill","hd":false},{"ty":"tr","p":{"a":0,"k":[886.814,153.132],"ix":2},"a":{"a":0,"k":[0,0],"ix":1},"s":{"a":0,"k":[100,100],"ix":3},"r":{"a":0,"k":0,"ix":6},"o":{"a":0,"k":100,"ix":7},"sk":{"a":0,"k":0,"ix":4},"sa":{"a":0,"k":0,"ix":5},"nm":"Transform"}],"nm":"Group 5","np":4,"cix":2,"bm":0,"ix":5,"mn":"ADBE Vector Group","hd":false},{"ty":"gr","it":[{"ind":0,"ty":"sh","ix":1,"ks":{"a":0,"k":{"i":[[0,0],[1.528,-0.45],[-0.46,-1.525],[0,0],[-2.221,-0.584]],"o":[[-0.46,-1.523],[-1.524,0.461],[0,0],[2.178,0.687],[0,0]],"v":[[-7.504,-33.522],[-11.099,-35.448],[-13.025,-31.853],[6.884,33.997],[13.485,35.898]],"c":true},"ix":2},"nm":"Path 1","mn":"ADBE Vector Shape - Group","hd":false},{"ty":"fl","c":{"a":0,"k":[0.6,0.875,0.722000002394,1],"ix":4},"o":{"a":0,"k":100,"ix":5},"r":1,"bm":0,"nm":"Fill 1","mn":"ADBE Vector Graphic - Fill","hd":false},{"ty":"tr","p":{"a":0,"k":[92.94,387.764],"ix":2},"a":{"a":0,"k":[0,0],"ix":1},"s":{"a":0,"k":[100,100],"ix":3},"r":{"a":0,"k":0,"ix":6},"o":{"a":0,"k":100,"ix":7},"sk":{"a":0,"k":0,"ix":4},"sa":{"a":0,"k":0,"ix":5},"nm":"Transform"}],"nm":"Group 6","np":4,"cix":2,"bm":0,"ix":6,"mn":"ADBE Vector Group","hd":false},{"ty":"gr","it":[{"ind":0,"ty":"sh","ix":1,"ks":{"a":0,"k":{"i":[[0,0],[11.963,-3.502],[-2.265,-12.257],[0,0],[-0.156,-0.616],[-15.471,-3.597],[5.517,13.543]],"o":[[-4.703,-11.544],[-11.963,3.502],[0,0],[0.115,0.625],[13.08,8.183],[12.218,-7.231],[0,0]],"v":[[12.69,-31.005],[-16.65,-45.162],[-33.723,-17.419],[-25.158,28.928],[-24.717,30.781],[18.336,48.664],[30.471,12.643]],"c":true},"ix":2},"nm":"Path 1","mn":"ADBE Vector Shape - Group","hd":false},{"ty":"fl","c":{"a":0,"k":[0.8,0.936999990426,0.859000052658,1],"ix":4},"o":{"a":0,"k":100,"ix":5},"r":1,"bm":0,"nm":"Fill 1","mn":"ADBE Vector Graphic - Fill","hd":false},{"ty":"tr","p":{"a":0,"k":[91.996,375.936],"ix":2},"a":{"a":0,"k":[0,0],"ix":1},"s":{"a":0,"k":[100,100],"ix":3},"r":{"a":0,"k":0,"ix":6},"o":{"a":0,"k":100,"ix":7},"sk":{"a":0,"k":0,"ix":4},"sa":{"a":0,"k":0,"ix":5},"nm":"Transform"}],"nm":"Group 7","np":4,"cix":2,"bm":0,"ix":7,"mn":"ADBE Vector Group","hd":false},{"ty":"gr","it":[{"ind":0,"ty":"sh","ix":1,"ks":{"a":0,"k":{"i":[[1.592,0.005],[0,0],[0.005,-1.589],[0,0],[-1.934,-0.074],[0,0]],"o":[[0,0],[-1.589,0],[0,0],[1.913,0.15],[0,0],[0.005,-1.593]],"v":[[0.254,-84.569],[0.245,-84.569],[-2.639,-81.694],[-3.134,84.222],[2.633,84.568],[3.129,-81.676]],"c":true},"ix":2},"nm":"Path 1","mn":"ADBE Vector Shape - Group","hd":false},{"ty":"fl","c":{"a":0,"k":[0.4,0.816000007181,0.583999992819,1],"ix":4},"o":{"a":0,"k":100,"ix":5},"r":1,"bm":0,"nm":"Fill 1","mn":"ADBE Vector Graphic - Fill","hd":false},{"ty":"tr","p":{"a":0,"k":[134.553,343.632],"ix":2},"a":{"a":0,"k":[0,0],"ix":1},"s":{"a":0,"k":[100,100],"ix":3},"r":{"a":0,"k":0,"ix":6},"o":{"a":0,"k":100,"ix":7},"sk":{"a":0,"k":0,"ix":4},"sa":{"a":0,"k":0,"ix":5},"nm":"Transform"}],"nm":"Group 8","np":4,"cix":2,"bm":0,"ix":8,"mn":"ADBE Vector Group","hd":false},{"ty":"gr","it":[{"ind":0,"ty":"sh","ix":1,"ks":{"a":0,"k":{"i":[[0.548,12.157],[0,0],[12.29,0.048],[0.652,-12.272],[0,0],[0.002,-0.503],[-7.122,-5.653],[-9.913,0],[0,0]],"o":[[0,0],[-0.555,-12.277],[-12.289,-0.049],[0,0],[-0.027,0.502],[-0.04,9.799],[9.341,1.928],[0,0],[10.028,-5.434]],"v":[[30.454,74.873],[23.409,-81.203],[0.475,-103.211],[-22.632,-81.385],[-30.919,74.628],[-30.962,76.136],[-19.311,100.313],[9.617,103.259],[14.36,103.259]],"c":true},"ix":2},"nm":"Path 1","mn":"ADBE Vector Shape - Group","hd":false},{"ty":"fl","c":{"a":0,"k":[0.6,0.875,0.722000002394,1],"ix":4},"o":{"a":0,"k":100,"ix":5},"r":1,"bm":0,"nm":"Fill 1","mn":"ADBE Vector Graphic - Fill","hd":false},{"ty":"tr","p":{"a":0,"k":[133.085,325.081],"ix":2},"a":{"a":0,"k":[0,0],"ix":1},"s":{"a":0,"k":[100,100],"ix":3},"r":{"a":0,"k":0,"ix":6},"o":{"a":0,"k":100,"ix":7},"sk":{"a":0,"k":0,"ix":4},"sa":{"a":0,"k":0,"ix":5},"nm":"Transform"}],"nm":"Group 9","np":4,"cix":2,"bm":0,"ix":9,"mn":"ADBE Vector Group","hd":false},{"ty":"gr","it":[{"ind":0,"ty":"sh","ix":1,"ks":{"a":0,"k":{"i":[[0,0],[1.502,0.529],[0.529,-1.504],[0,0],[0,0]],"o":[[0.529,-1.502],[-1.502,-0.531],[0,0],[0,0],[0,0]],"v":[[26.385,-65.009],[24.621,-68.686],[20.944,-66.921],[-26.915,69.216],[-20.802,69.216]],"c":true},"ix":2},"nm":"Path 1","mn":"ADBE Vector Shape - Group","hd":false},{"ty":"fl","c":{"a":0,"k":[0.6,0.875,0.722000002394,1],"ix":4},"o":{"a":0,"k":100,"ix":5},"r":1,"bm":0,"nm":"Fill 1","mn":"ADBE Vector Graphic - Fill","hd":false},{"ty":"tr","p":{"a":0,"k":[190.762,359.123],"ix":2},"a":{"a":0,"k":[0,0],"ix":1},"s":{"a":0,"k":[100,100],"ix":3},"r":{"a":0,"k":0,"ix":6},"o":{"a":0,"k":100,"ix":7},"sk":{"a":0,"k":0,"ix":4},"sa":{"a":0,"k":0,"ix":5},"nm":"Transform"}],"nm":"Group 10","np":4,"cix":2,"bm":0,"ix":10,"mn":"ADBE Vector Group","hd":false},{"ty":"gr","it":[{"ind":0,"ty":"sh","ix":1,"ks":{"a":0,"k":{"i":[[0,0],[11.57,4.143],[4.706,-11.352],[0,0],[-0.553,-4.981],[-1.508,0],[0,0]],"o":[[3.571,-11.759],[-11.57,-4.144],[0,0],[-2.055,4.958],[1.497,0.047],[0,0],[0,0]],"v":[[51.156,-55.751],[36.873,-84.146],[7.811,-71.274],[-52.018,73.05],[-54.174,88.175],[-49.678,88.29],[7.418,88.29]],"c":true},"ix":2},"nm":"Path 1","mn":"ADBE Vector Shape - Group","hd":false},{"ty":"fl","c":{"a":0,"k":[0.8,0.936999990426,0.859000052658,1],"ix":4},"o":{"a":0,"k":100,"ix":5},"r":1,"bm":0,"nm":"Fill 1","mn":"ADBE Vector Graphic - Fill","hd":false},{"ty":"tr","p":{"a":0,"k":[192.38,340.05],"ix":2},"a":{"a":0,"k":[0,0],"ix":1},"s":{"a":0,"k":[100,100],"ix":3},"r":{"a":0,"k":0,"ix":6},"o":{"a":0,"k":100,"ix":7},"sk":{"a":0,"k":0,"ix":4},"sa":{"a":0,"k":0,"ix":5},"nm":"Transform"}],"nm":"Group 11","np":4,"cix":2,"bm":0,"ix":11,"mn":"ADBE Vector Group","hd":false},{"ty":"gr","it":[{"ind":0,"ty":"sh","ix":1,"ks":{"a":0,"k":{"i":[[0,0],[-4.537,-0.43],[9.853,2.372]],"o":[[4.044,2.103],[0,0],[0,0]],"v":[[-6.496,-3.398],[6.496,0.437],[-6.496,1.026]],"c":true},"ix":2},"nm":"Path 1","mn":"ADBE Vector Shape - Group","hd":false},{"ty":"fl","c":{"a":0,"k":[0.898000021542,0.651000019148,0.46699999641,1],"ix":4},"o":{"a":0,"k":100,"ix":5},"r":1,"bm":0,"nm":"Fill 1","mn":"ADBE Vector Graphic - Fill","hd":false},{"ty":"tr","p":{"a":0,"k":[692.715,274.104],"ix":2},"a":{"a":0,"k":[0,0],"ix":1},"s":{"a":0,"k":[100,100],"ix":3},"r":{"a":0,"k":0,"ix":6},"o":{"a":0,"k":100,"ix":7},"sk":{"a":0,"k":0,"ix":4},"sa":{"a":0,"k":0,"ix":5},"nm":"Transform"}],"nm":"Group 12","np":4,"cix":2,"bm":0,"ix":12,"mn":"ADBE Vector Group","hd":false},{"ty":"gr","it":[{"ind":0,"ty":"sh","ix":1,"ks":{"a":0,"k":{"i":[[0,0],[0,0],[0,0],[0,0]],"o":[[0,0],[0,0],[0,0],[0,0]],"v":[[7.56,-25.156],[-2.871,-18.047],[-7.56,25.157],[7.56,25.157]],"c":true},"ix":2},"nm":"Path 1","mn":"ADBE Vector Shape - Group","hd":false},{"ty":"fl","c":{"a":0,"k":[0,0.556999954523,0.246999987434,1],"ix":4},"o":{"a":0,"k":100,"ix":5},"r":1,"bm":0,"nm":"Fill 1","mn":"ADBE Vector Graphic - Fill","hd":false},{"ty":"tr","p":{"a":0,"k":[632.842,403.184],"ix":2},"a":{"a":0,"k":[0,0],"ix":1},"s":{"a":0,"k":[100,100],"ix":3},"r":{"a":0,"k":0,"ix":6},"o":{"a":0,"k":100,"ix":7},"sk":{"a":0,"k":0,"ix":4},"sa":{"a":0,"k":0,"ix":5},"nm":"Transform"}],"nm":"Group 13","np":4,"cix":2,"bm":0,"ix":13,"mn":"ADBE Vector Group","hd":false},{"ty":"gr","it":[{"ind":0,"ty":"sh","ix":1,"ks":{"a":0,"k":{"i":[[0,0],[0,0],[0,0],[0,0]],"o":[[0,0],[0,0],[0,0],[0,0]],"v":[[26.959,6.93],[-26.959,6.93],[-21.966,-6.93],[21.966,-6.93]],"c":true},"ix":2},"nm":"Path 1","mn":"ADBE Vector Shape - Group","hd":false},{"ty":"fl","c":{"a":0,"k":[1,1,1,1],"ix":4},"o":{"a":0,"k":100,"ix":5},"r":1,"bm":0,"nm":"Fill 1","mn":"ADBE Vector Graphic - Fill","hd":false},{"ty":"tr","p":{"a":0,"k":[701.524,285.005],"ix":2},"a":{"a":0,"k":[0,0],"ix":1},"s":{"a":0,"k":[100,100],"ix":3},"r":{"a":0,"k":0,"ix":6},"o":{"a":0,"k":100,"ix":7},"sk":{"a":0,"k":0,"ix":4},"sa":{"a":0,"k":0,"ix":5},"nm":"Transform"}],"nm":"Group 14","np":4,"cix":2,"bm":0,"ix":14,"mn":"ADBE Vector Group","hd":false},{"ty":"gr","it":[{"ind":0,"ty":"sh","ix":1,"ks":{"a":0,"k":{"i":[[0,0],[0,0],[0.923,8.956],[-0.128,6.059],[0,0]],"o":[[0,0],[0,0],[-0.572,-6.033],[0,0],[0,0]],"v":[[-16.086,17.813],[16.086,17.813],[13.295,0.341],[12.628,-17.813],[-16.086,-17.813]],"c":false},"ix":2},"nm":"Path 1","mn":"ADBE Vector Shape - Group","hd":false},{"ty":"fl","c":{"a":0,"k":[0.976000019148,0.728999956916,0.541000007181,1],"ix":4},"o":{"a":0,"k":100,"ix":5},"r":1,"bm":0,"nm":"Fill 1","mn":"ADBE Vector Graphic - Fill","hd":false},{"ty":"tr","p":{"a":0,"k":[702.348,269.414],"ix":2},"a":{"a":0,"k":[0,0],"ix":1},"s":{"a":0,"k":[100,100],"ix":3},"r":{"a":0,"k":0,"ix":6},"o":{"a":0,"k":100,"ix":7},"sk":{"a":0,"k":0,"ix":4},"sa":{"a":0,"k":0,"ix":5},"nm":"Transform"}],"nm":"Group 15","np":4,"cix":2,"bm":0,"ix":15,"mn":"ADBE Vector Group","hd":false},{"ty":"gr","it":[{"ind":0,"ty":"sh","ix":1,"ks":{"a":0,"k":{"i":[[0,0],[8.874,23.439],[0,0],[0,0],[16.702,-18.187],[0,0]],"o":[[-1.915,-29.39],[-12.074,-31.895],[0,0],[0,0],[-10.848,11.813],[0,0]],"v":[[106.709,68.202],[95.615,-16.037],[55.731,-68.202],[5.479,-68.202],[-25.1,-43.589],[-45.651,68.202]],"c":true},"ix":2},"nm":"Path 1","mn":"ADBE Vector Shape - Group","hd":false},{"ty":"fl","c":{"a":0,"k":[0,0.694000004787,0.310000011968,1],"ix":4},"o":{"a":0,"k":100,"ix":5},"r":1,"bm":0,"nm":"Fill 1","mn":"ADBE Vector Graphic - Fill","hd":false},{"ty":"tr","p":{"a":0,"k":[670.932,360.138],"ix":2},"a":{"a":0,"k":[0,0],"ix":1},"s":{"a":0,"k":[100,100],"ix":3},"r":{"a":0,"k":0,"ix":6},"o":{"a":0,"k":100,"ix":7},"sk":{"a":0,"k":0,"ix":4},"sa":{"a":0,"k":0,"ix":5},"nm":"Transform"}],"nm":"Group 17","np":4,"cix":2,"bm":0,"ix":16,"mn":"ADBE Vector Group","hd":false},{"ty":"gr","it":[{"ind":0,"ty":"sh","ix":1,"ks":{"a":0,"k":{"i":[[0,0],[0,0],[0,0],[0,0]],"o":[[0,0],[0,0],[0,0],[0,0]],"v":[[72.352,5.454],[-72.352,5.454],[-72.352,-5.454],[72.352,-5.454]],"c":true},"ix":2},"nm":"Path 1","mn":"ADBE Vector Shape - Group","hd":false},{"ty":"fl","c":{"a":0,"k":[0.8,0.936999990426,0.862999949736,1],"ix":4},"o":{"a":0,"k":100,"ix":5},"r":1,"bm":0,"nm":"Fill 1","mn":"ADBE Vector Graphic - Fill","hd":false},{"ty":"tr","p":{"a":0,"k":[390.836,155.489],"ix":2},"a":{"a":0,"k":[0,0],"ix":1},"s":{"a":0,"k":[100,100],"ix":3},"r":{"a":0,"k":0,"ix":6},"o":{"a":0,"k":100,"ix":7},"sk":{"a":0,"k":0,"ix":4},"sa":{"a":0,"k":0,"ix":5},"nm":"Transform"}],"nm":"Group 18","np":4,"cix":2,"bm":0,"ix":17,"mn":"ADBE Vector Group","hd":false},{"ty":"gr","it":[{"ind":0,"ty":"sh","ix":1,"ks":{"a":0,"k":{"i":[[0,0],[0,0],[0,0],[0,0]],"o":[[0,0],[0,0],[0,0],[0,0]],"v":[[72.352,5.454],[-72.352,5.454],[-72.352,-5.454],[72.352,-5.454]],"c":true},"ix":2},"nm":"Path 1","mn":"ADBE Vector Shape - Group","hd":false},{"ty":"fl","c":{"a":0,"k":[0.8,0.936999990426,0.862999949736,1],"ix":4},"o":{"a":0,"k":100,"ix":5},"r":1,"bm":0,"nm":"Fill 1","mn":"ADBE Vector Graphic - Fill","hd":false},{"ty":"tr","p":{"a":0,"k":[390.836,209.561],"ix":2},"a":{"a":0,"k":[0,0],"ix":1},"s":{"a":0,"k":[100,100],"ix":3},"r":{"a":0,"k":0,"ix":6},"o":{"a":0,"k":100,"ix":7},"sk":{"a":0,"k":0,"ix":4},"sa":{"a":0,"k":0,"ix":5},"nm":"Transform"}],"nm":"Group 19","np":4,"cix":2,"bm":0,"ix":18,"mn":"ADBE Vector Group","hd":false},{"ty":"gr","it":[{"ind":0,"ty":"sh","ix":1,"ks":{"a":0,"k":{"i":[[0,0],[0,0],[0,0],[0,0]],"o":[[0,0],[0,0],[0,0],[0,0]],"v":[[72.352,5.454],[-72.352,5.454],[-72.352,-5.454],[72.352,-5.454]],"c":true},"ix":2},"nm":"Path 1","mn":"ADBE Vector Shape - Group","hd":false},{"ty":"fl","c":{"a":0,"k":[0.8,0.936999990426,0.862999949736,1],"ix":4},"o":{"a":0,"k":100,"ix":5},"r":1,"bm":0,"nm":"Fill 1","mn":"ADBE Vector Graphic - Fill","hd":false},{"ty":"tr","p":{"a":0,"k":[390.836,182.526],"ix":2},"a":{"a":0,"k":[0,0],"ix":1},"s":{"a":0,"k":[100,100],"ix":3},"r":{"a":0,"k":0,"ix":6},"o":{"a":0,"k":100,"ix":7},"sk":{"a":0,"k":0,"ix":4},"sa":{"a":0,"k":0,"ix":5},"nm":"Transform"}],"nm":"Group 20","np":4,"cix":2,"bm":0,"ix":19,"mn":"ADBE Vector Group","hd":false},{"ty":"gr","it":[{"ind":0,"ty":"sh","ix":1,"ks":{"a":0,"k":{"i":[[0,0],[0,0],[0,0],[0,0]],"o":[[0,0],[0,0],[0,0],[0,0]],"v":[[107.686,5.454],[-107.686,5.454],[-107.686,-5.454],[107.686,-5.454]],"c":true},"ix":2},"nm":"Path 1","mn":"ADBE Vector Shape - Group","hd":false},{"ty":"fl","c":{"a":0,"k":[0.8,0.936999990426,0.862999949736,1],"ix":4},"o":{"a":0,"k":100,"ix":5},"r":1,"bm":0,"nm":"Fill 1","mn":"ADBE Vector Graphic - Fill","hd":false},{"ty":"tr","p":{"a":0,"k":[426.171,249.745],"ix":2},"a":{"a":0,"k":[0,0],"ix":1},"s":{"a":0,"k":[100,100],"ix":3},"r":{"a":0,"k":0,"ix":6},"o":{"a":0,"k":100,"ix":7},"sk":{"a":0,"k":0,"ix":4},"sa":{"a":0,"k":0,"ix":5},"nm":"Transform"}],"nm":"Group 21","np":4,"cix":2,"bm":0,"ix":20,"mn":"ADBE Vector Group","hd":false},{"ty":"gr","it":[{"ind":0,"ty":"sh","ix":1,"ks":{"a":0,"k":{"i":[[0,0],[0,0],[0,0],[0,0]],"o":[[0,0],[0,0],[0,0],[0,0]],"v":[[107.686,5.454],[-107.686,5.454],[-107.686,-5.454],[107.686,-5.454]],"c":true},"ix":2},"nm":"Path 1","mn":"ADBE Vector Shape - Group","hd":false},{"ty":"fl","c":{"a":0,"k":[0.8,0.936999990426,0.862999949736,1],"ix":4},"o":{"a":0,"k":100,"ix":5},"r":1,"bm":0,"nm":"Fill 1","mn":"ADBE Vector Graphic - Fill","hd":false},{"ty":"tr","p":{"a":0,"k":[426.171,303.817],"ix":2},"a":{"a":0,"k":[0,0],"ix":1},"s":{"a":0,"k":[100,100],"ix":3},"r":{"a":0,"k":0,"ix":6},"o":{"a":0,"k":100,"ix":7},"sk":{"a":0,"k":0,"ix":4},"sa":{"a":0,"k":0,"ix":5},"nm":"Transform"}],"nm":"Group 22","np":4,"cix":2,"bm":0,"ix":21,"mn":"ADBE Vector Group","hd":false},{"ty":"gr","it":[{"ind":0,"ty":"sh","ix":1,"ks":{"a":0,"k":{"i":[[0,0],[0,0],[0,0],[0,0]],"o":[[0,0],[0,0],[0,0],[0,0]],"v":[[107.686,5.454],[-107.686,5.454],[-107.686,-5.454],[107.686,-5.454]],"c":true},"ix":2},"nm":"Path 1","mn":"ADBE Vector Shape - Group","hd":false},{"ty":"fl","c":{"a":0,"k":[0.8,0.936999990426,0.862999949736,1],"ix":4},"o":{"a":0,"k":100,"ix":5},"r":1,"bm":0,"nm":"Fill 1","mn":"ADBE Vector Graphic - Fill","hd":false},{"ty":"tr","p":{"a":0,"k":[426.171,276.782],"ix":2},"a":{"a":0,"k":[0,0],"ix":1},"s":{"a":0,"k":[100,100],"ix":3},"r":{"a":0,"k":0,"ix":6},"o":{"a":0,"k":100,"ix":7},"sk":{"a":0,"k":0,"ix":4},"sa":{"a":0,"k":0,"ix":5},"nm":"Transform"}],"nm":"Group 23","np":4,"cix":2,"bm":0,"ix":22,"mn":"ADBE Vector Group","hd":false},{"ty":"gr","it":[{"ind":0,"ty":"sh","ix":1,"ks":{"a":0,"k":{"i":[[0,0],[2.445,2.445],[0,0],[3.458,0],[0,0],[-7.554,0]],"o":[[0,-3.458],[0,0],[-2.445,-2.445],[0,0],[0,7.554],[0,0]],"v":[[37.34,37.34],[33.521,28.121],[-28.12,-33.521],[-37.34,-37.34],[-37.34,23.663],[-23.663,37.34]],"c":true},"ix":2},"nm":"Path 1","mn":"ADBE Vector Shape - Group","hd":false},{"ty":"fl","c":{"a":0,"k":[0.6,0.877999997606,0.725,1],"ix":4},"o":{"a":0,"k":100,"ix":5},"r":1,"bm":0,"nm":"Fill 1","mn":"ADBE Vector Graphic - Fill","hd":false},{"ty":"tr","p":{"a":0,"k":[534.274,121.165],"ix":2},"a":{"a":0,"k":[0,0],"ix":1},"s":{"a":0,"k":[100,100],"ix":3},"r":{"a":0,"k":0,"ix":6},"o":{"a":0,"k":100,"ix":7},"sk":{"a":0,"k":0,"ix":4},"sa":{"a":0,"k":0,"ix":5},"nm":"Transform"}],"nm":"Group 24","np":4,"cix":2,"bm":0,"ix":23,"mn":"ADBE Vector Group","hd":false},{"ty":"gr","it":[{"ind":0,"ty":"sh","ix":1,"ks":{"a":0,"k":{"i":[[0,0],[0.842,1.748],[0,0],[3.458,0],[0,0],[-7.554,0],[0,0]],"o":[[0,-1.977],[0,0],[-2.445,-2.445],[0,0],[0,7.554],[0,0],[0,0]],"v":[[33.522,28.649],[32.217,22.999],[-24.303,-33.521],[-33.522,-37.34],[-33.522,23.663],[-19.845,37.34],[33.522,37.34]],"c":true},"ix":2},"nm":"Path 1","mn":"ADBE Vector Shape - Group","hd":false},{"ty":"fl","c":{"a":0,"k":[0.501999978458,0.847000002394,0.654999976065,1],"ix":4},"o":{"a":0,"k":100,"ix":5},"r":1,"bm":0,"nm":"Fill 1","mn":"ADBE Vector Graphic - Fill","hd":false},{"ty":"tr","p":{"a":0,"k":[538.092,129.856],"ix":2},"a":{"a":0,"k":[0,0],"ix":1},"s":{"a":0,"k":[100,100],"ix":3},"r":{"a":0,"k":0,"ix":6},"o":{"a":0,"k":100,"ix":7},"sk":{"a":0,"k":0,"ix":4},"sa":{"a":0,"k":0,"ix":5},"nm":"Transform"}],"nm":"Group 25","np":4,"cix":2,"bm":0,"ix":24,"mn":"ADBE Vector Group","hd":false},{"ty":"gr","it":[{"ind":0,"ty":"sh","ix":1,"ks":{"a":0,"k":{"i":[[0,0.138],[0,0],[2.445,2.445],[0,0],[3.458,0],[0,0],[0,-16.394],[0,0],[-0.007,-0.137],[0,0]],"o":[[0,0],[0,-3.458],[0,0],[-2.445,-2.445],[0,0],[-16.394,0],[0,0],[0,0.138],[0,0],[0.007,-0.137]],"v":[[145.444,171.849],[145.444,-97.577],[141.624,-106.797],[79.983,-168.438],[70.763,-172.257],[-115.76,-172.257],[-145.444,-142.573],[-145.444,171.849],[-145.423,172.257],[145.422,172.257]],"c":true},"ix":2},"nm":"Path 1","mn":"ADBE Vector Shape - Group","hd":false},{"ty":"fl","c":{"a":0,"k":[0.698000021542,0.910000011968,0.791999966491,1],"ix":4},"o":{"a":0,"k":100,"ix":5},"r":1,"bm":0,"nm":"Fill 1","mn":"ADBE Vector Graphic - Fill","hd":false},{"ty":"tr","p":{"a":0,"k":[426.171,256.083],"ix":2},"a":{"a":0,"k":[0,0],"ix":1},"s":{"a":0,"k":[100,100],"ix":3},"r":{"a":0,"k":0,"ix":6},"o":{"a":0,"k":100,"ix":7},"sk":{"a":0,"k":0,"ix":4},"sa":{"a":0,"k":0,"ix":5},"nm":"Transform"}],"nm":"Group 26","np":4,"cix":2,"bm":0,"ix":25,"mn":"ADBE Vector Group","hd":false},{"ty":"gr","it":[{"ind":0,"ty":"sh","ix":1,"ks":{"a":0,"k":{"i":[[0,5.995],[0,0],[9.193,0],[0,0],[0,-9.193],[0,0],[-4.754,-2.931],[0,0]],"o":[[0,0],[0,-9.193],[0,0],[-9.193,0],[0,0],[0,5.995],[0,0],[4.755,-2.931]],"v":[[145.444,171.504],[145.444,-168.994],[128.798,-185.64],[-128.798,-185.64],[-145.444,-168.994],[-145.444,171.504],[-137.492,185.64],[137.491,185.64]],"c":true},"ix":2},"nm":"Path 1","mn":"ADBE Vector Shape - Group","hd":false},{"ty":"fl","c":{"a":0,"k":[0.8,0.936999990426,0.862999949736,1],"ix":4},"o":{"a":0,"k":100,"ix":5},"r":1,"bm":0,"nm":"Fill 1","mn":"ADBE Vector Graphic - Fill","hd":false},{"ty":"tr","p":{"a":0,"k":[479.419,242.7],"ix":2},"a":{"a":0,"k":[0,0],"ix":1},"s":{"a":0,"k":[100,100],"ix":3},"r":{"a":0,"k":0,"ix":6},"o":{"a":0,"k":100,"ix":7},"sk":{"a":0,"k":0,"ix":4},"sa":{"a":0,"k":0,"ix":5},"nm":"Transform"}],"nm":"Group 27","np":4,"cix":2,"bm":0,"ix":26,"mn":"ADBE Vector Group","hd":false},{"ty":"gr","it":[{"ind":0,"ty":"sh","ix":1,"ks":{"a":0,"k":{"i":[[0,0],[0,0],[0,0],[0,0]],"o":[[0,0],[0,0],[0,0],[0,0]],"v":[[-118.039,-185.803],[-128.797,-185.803],[-128.879,-187.987],[-118.039,-187.987]],"c":true},"ix":2},"nm":"Path 1","mn":"ADBE Vector Shape - Group","hd":false},{"ind":1,"ty":"sh","ix":2,"ks":{"a":0,"k":{"i":[[0,0],[0,0],[0,0],[0,0]],"o":[[0,0],[0,0],[0,0],[0,0]],"v":[[-96.363,-185.803],[-107.201,-185.803],[-107.201,-187.987],[-96.363,-187.987]],"c":true},"ix":2},"nm":"Path 2","mn":"ADBE Vector Shape - Group","hd":false},{"ind":2,"ty":"sh","ix":3,"ks":{"a":0,"k":{"i":[[0,0],[0,0],[0,0],[0,0]],"o":[[0,0],[0,0],[0,0],[0,0]],"v":[[-74.685,-185.803],[-85.522,-185.803],[-85.522,-187.987],[-74.685,-187.987]],"c":true},"ix":2},"nm":"Path 3","mn":"ADBE Vector Shape - Group","hd":false},{"ind":3,"ty":"sh","ix":4,"ks":{"a":0,"k":{"i":[[0,0],[0,0],[0,0],[0,0]],"o":[[0,0],[0,0],[0,0],[0,0]],"v":[[-53.008,-185.803],[-63.846,-185.803],[-63.846,-187.987],[-53.008,-187.987]],"c":true},"ix":2},"nm":"Path 4","mn":"ADBE Vector Shape - Group","hd":false},{"ind":4,"ty":"sh","ix":5,"ks":{"a":0,"k":{"i":[[0,0],[0,0],[0,0],[0,0]],"o":[[0,0],[0,0],[0,0],[0,0]],"v":[[-31.329,-185.803],[-42.168,-185.803],[-42.168,-187.987],[-31.329,-187.987]],"c":true},"ix":2},"nm":"Path 5","mn":"ADBE Vector Shape - Group","hd":false},{"ind":5,"ty":"sh","ix":6,"ks":{"a":0,"k":{"i":[[0,0],[0,0],[0,0],[0,0]],"o":[[0,0],[0,0],[0,0],[0,0]],"v":[[-9.652,-185.803],[-20.49,-185.803],[-20.49,-187.987],[-9.652,-187.987]],"c":true},"ix":2},"nm":"Path 6","mn":"ADBE Vector Shape - Group","hd":false},{"ind":6,"ty":"sh","ix":7,"ks":{"a":0,"k":{"i":[[0,0],[0,0],[0,0],[0,0]],"o":[[0,0],[0,0],[0,0],[0,0]],"v":[[12.026,-185.803],[1.188,-185.803],[1.188,-187.987],[12.026,-187.987]],"c":true},"ix":2},"nm":"Path 7","mn":"ADBE Vector Shape - Group","hd":false},{"ind":7,"ty":"sh","ix":8,"ks":{"a":0,"k":{"i":[[0,0],[0,0],[0,0],[0,0]],"o":[[0,0],[0,0],[0,0],[0,0]],"v":[[33.704,-185.803],[22.866,-185.803],[22.866,-187.987],[33.704,-187.987]],"c":true},"ix":2},"nm":"Path 8","mn":"ADBE Vector Shape - Group","hd":false},{"ind":8,"ty":"sh","ix":9,"ks":{"a":0,"k":{"i":[[0,0],[0,0],[0,0],[0,0]],"o":[[0,0],[0,0],[0,0],[0,0]],"v":[[55.381,-185.803],[44.542,-185.803],[44.542,-187.987],[55.381,-187.987]],"c":true},"ix":2},"nm":"Path 9","mn":"ADBE Vector Shape - Group","hd":false},{"ind":9,"ty":"sh","ix":10,"ks":{"a":0,"k":{"i":[[0,0],[0,0],[0,0],[0,0]],"o":[[0,0],[0,0],[0,0],[0,0]],"v":[[77.058,-185.803],[66.22,-185.803],[66.22,-187.987],[77.058,-187.987]],"c":true},"ix":2},"nm":"Path 10","mn":"ADBE Vector Shape - Group","hd":false},{"ind":10,"ty":"sh","ix":11,"ks":{"a":0,"k":{"i":[[0,0],[0,0],[0,0],[0,0]],"o":[[0,0],[0,0],[0,0],[0,0]],"v":[[98.736,-185.803],[87.898,-185.803],[87.898,-187.987],[98.736,-187.987]],"c":true},"ix":2},"nm":"Path 11","mn":"ADBE Vector Shape - Group","hd":false},{"ind":11,"ty":"sh","ix":12,"ks":{"a":0,"k":{"i":[[0,0],[0,0],[0,0],[0,0]],"o":[[0,0],[0,0],[0,0],[0,0]],"v":[[120.413,-185.803],[109.575,-185.803],[109.575,-187.987],[120.413,-187.987]],"c":true},"ix":2},"nm":"Path 12","mn":"ADBE Vector Shape - Group","hd":false},{"ind":12,"ty":"sh","ix":13,"ks":{"a":0,"k":{"i":[[0,0],[3.34,0.492],[0,0],[-2.703,-2.771]],"o":[[-2.371,-2.43],[0,0],[3.81,0.561],[0,0]],"v":[[139.943,-181.104],[131.087,-185.636],[131.403,-187.795],[141.504,-182.627]],"c":true},"ix":2},"nm":"Path 13","mn":"ADBE Vector Shape - Group","hd":false},{"ind":13,"ty":"sh","ix":14,"ks":{"a":0,"k":{"i":[[0.878,-3.259],[0,0],[-3.066,2.36],[0,0]],"o":[[0,0],[1.003,-3.72],[0,0],[-2.691,2.07]],"v":[[-143.815,-174.315],[-145.923,-174.881],[-139.613,-184.308],[-138.281,-182.58]],"c":true},"ix":2},"nm":"Path 14","mn":"ADBE Vector Shape - Group","hd":false},{"ind":14,"ty":"sh","ix":15,"ks":{"a":0,"k":{"i":[[0,0],[0,0],[0,0],[0.075,0.62],[0,0],[0,-0.726]],"o":[[0,0],[0,0],[0,-0.639],[0,0],[0.085,0.704],[0,0]],"v":[[146.536,-161.435],[144.353,-161.435],[144.353,-170.249],[144.24,-172.138],[146.406,-172.399],[146.536,-170.249]],"c":true},"ix":2},"nm":"Path 15","mn":"ADBE Vector Shape - Group","hd":false},{"ind":15,"ty":"sh","ix":16,"ks":{"a":0,"k":{"i":[[0,0],[0,0],[0,0],[0,0]],"o":[[0,0],[0,0],[0,0],[0,0]],"v":[[-144.352,-152.97],[-146.535,-152.97],[-146.535,-163.808],[-144.352,-163.808]],"c":true},"ix":2},"nm":"Path 16","mn":"ADBE Vector Shape - Group","hd":false},{"ind":16,"ty":"sh","ix":17,"ks":{"a":0,"k":{"i":[[0,0],[0,0],[0,0],[0,0]],"o":[[0,0],[0,0],[0,0],[0,0]],"v":[[146.536,-139.759],[144.353,-139.759],[144.353,-150.597],[146.536,-150.597]],"c":true},"ix":2},"nm":"Path 17","mn":"ADBE Vector Shape - Group","hd":false},{"ind":17,"ty":"sh","ix":18,"ks":{"a":0,"k":{"i":[[0,0],[0,0],[0,0],[0,0]],"o":[[0,0],[0,0],[0,0],[0,0]],"v":[[-144.352,-131.293],[-146.535,-131.293],[-146.535,-142.131],[-144.352,-142.131]],"c":true},"ix":2},"nm":"Path 18","mn":"ADBE Vector Shape - Group","hd":false},{"ind":18,"ty":"sh","ix":19,"ks":{"a":0,"k":{"i":[[0,0],[0,0],[0,0],[0,0]],"o":[[0,0],[0,0],[0,0],[0,0]],"v":[[146.536,-118.08],[144.353,-118.08],[144.353,-128.92],[146.536,-128.92]],"c":true},"ix":2},"nm":"Path 19","mn":"ADBE Vector Shape - Group","hd":false},{"ind":19,"ty":"sh","ix":20,"ks":{"a":0,"k":{"i":[[0,0],[0,0],[0,0],[0,0]],"o":[[0,0],[0,0],[0,0],[0,0]],"v":[[-144.352,-109.615],[-146.535,-109.615],[-146.535,-120.454],[-144.352,-120.454]],"c":true},"ix":2},"nm":"Path 20","mn":"ADBE Vector Shape - Group","hd":false},{"ind":20,"ty":"sh","ix":21,"ks":{"a":0,"k":{"i":[[0,0],[0,0],[0,0],[0,0]],"o":[[0,0],[0,0],[0,0],[0,0]],"v":[[146.536,-96.403],[144.353,-96.403],[144.353,-107.241],[146.536,-107.241]],"c":true},"ix":2},"nm":"Path 21","mn":"ADBE Vector Shape - Group","hd":false},{"ind":21,"ty":"sh","ix":22,"ks":{"a":0,"k":{"i":[[0,0],[0,0],[0,0],[0,0]],"o":[[0,0],[0,0],[0,0],[0,0]],"v":[[-144.352,-87.937],[-146.535,-87.937],[-146.535,-98.776],[-144.352,-98.776]],"c":true},"ix":2},"nm":"Path 22","mn":"ADBE Vector Shape - Group","hd":false},{"ind":22,"ty":"sh","ix":23,"ks":{"a":0,"k":{"i":[[0,0],[0,0],[0,0],[0,0]],"o":[[0,0],[0,0],[0,0],[0,0]],"v":[[146.536,-74.726],[144.353,-74.726],[144.353,-85.564],[146.536,-85.564]],"c":true},"ix":2},"nm":"Path 23","mn":"ADBE Vector Shape - Group","hd":false},{"ind":23,"ty":"sh","ix":24,"ks":{"a":0,"k":{"i":[[0,0],[0,0],[0,0],[0,0]],"o":[[0,0],[0,0],[0,0],[0,0]],"v":[[-144.352,-66.26],[-146.535,-66.26],[-146.535,-77.098],[-144.352,-77.098]],"c":true},"ix":2},"nm":"Path 24","mn":"ADBE Vector Shape - Group","hd":false},{"ind":24,"ty":"sh","ix":25,"ks":{"a":0,"k":{"i":[[0,0],[0,0],[0,0],[0,0]],"o":[[0,0],[0,0],[0,0],[0,0]],"v":[[146.536,-53.047],[144.353,-53.047],[144.353,-63.887],[146.536,-63.887]],"c":true},"ix":2},"nm":"Path 25","mn":"ADBE Vector Shape - Group","hd":false},{"ind":25,"ty":"sh","ix":26,"ks":{"a":0,"k":{"i":[[0,0],[0,0],[0,0],[0,0]],"o":[[0,0],[0,0],[0,0],[0,0]],"v":[[-144.352,-44.581],[-146.535,-44.581],[-146.535,-55.421],[-144.352,-55.421]],"c":true},"ix":2},"nm":"Path 26","mn":"ADBE Vector Shape - Group","hd":false},{"ind":26,"ty":"sh","ix":27,"ks":{"a":0,"k":{"i":[[0,0],[0,0],[0,0],[0,0]],"o":[[0,0],[0,0],[0,0],[0,0]],"v":[[146.536,-31.37],[144.353,-31.37],[144.353,-42.209],[146.536,-42.209]],"c":true},"ix":2},"nm":"Path 27","mn":"ADBE Vector Shape - Group","hd":false},{"ind":27,"ty":"sh","ix":28,"ks":{"a":0,"k":{"i":[[0,0],[0,0],[0,0],[0,0]],"o":[[0,0],[0,0],[0,0],[0,0]],"v":[[-144.352,-22.905],[-146.535,-22.905],[-146.535,-33.743],[-144.352,-33.743]],"c":true},"ix":2},"nm":"Path 28","mn":"ADBE Vector Shape - Group","hd":false},{"ind":28,"ty":"sh","ix":29,"ks":{"a":0,"k":{"i":[[0,0],[0,0],[0,0],[0,0]],"o":[[0,0],[0,0],[0,0],[0,0]],"v":[[146.536,-9.693],[144.353,-9.693],[144.353,-20.531],[146.536,-20.531]],"c":true},"ix":2},"nm":"Path 29","mn":"ADBE Vector Shape - Group","hd":false},{"ind":29,"ty":"sh","ix":30,"ks":{"a":0,"k":{"i":[[0,0],[0,0],[0,0],[0,0]],"o":[[0,0],[0,0],[0,0],[0,0]],"v":[[-144.352,-1.227],[-146.535,-1.227],[-146.535,-12.065],[-144.352,-12.065]],"c":true},"ix":2},"nm":"Path 30","mn":"ADBE Vector Shape - Group","hd":false},{"ind":30,"ty":"sh","ix":31,"ks":{"a":0,"k":{"i":[[0,0],[0,0],[0,0],[0,0]],"o":[[0,0],[0,0],[0,0],[0,0]],"v":[[146.536,11.986],[144.353,11.986],[144.353,1.148],[146.536,1.148]],"c":true},"ix":2},"nm":"Path 31","mn":"ADBE Vector Shape - Group","hd":false},{"ind":31,"ty":"sh","ix":32,"ks":{"a":0,"k":{"i":[[0,0],[0,0],[0,0],[0,0]],"o":[[0,0],[0,0],[0,0],[0,0]],"v":[[-144.352,20.451],[-146.535,20.451],[-146.535,9.613],[-144.352,9.613]],"c":true},"ix":2},"nm":"Path 32","mn":"ADBE Vector Shape - Group","hd":false},{"ind":32,"ty":"sh","ix":33,"ks":{"a":0,"k":{"i":[[0,0],[0,0],[0,0],[0,0]],"o":[[0,0],[0,0],[0,0],[0,0]],"v":[[146.536,33.662],[144.353,33.662],[144.353,22.824],[146.536,22.824]],"c":true},"ix":2},"nm":"Path 33","mn":"ADBE Vector Shape - Group","hd":false},{"ind":33,"ty":"sh","ix":34,"ks":{"a":0,"k":{"i":[[0,0],[0,0],[0,0],[0,0]],"o":[[0,0],[0,0],[0,0],[0,0]],"v":[[-144.352,42.128],[-146.535,42.128],[-146.535,31.29],[-144.352,31.29]],"c":true},"ix":2},"nm":"Path 34","mn":"ADBE Vector Shape - Group","hd":false},{"ind":34,"ty":"sh","ix":35,"ks":{"a":0,"k":{"i":[[0,0],[0,0],[0,0],[0,0]],"o":[[0,0],[0,0],[0,0],[0,0]],"v":[[146.536,55.341],[144.353,55.341],[144.353,44.501],[146.536,44.501]],"c":true},"ix":2},"nm":"Path 35","mn":"ADBE Vector Shape - Group","hd":false},{"ind":35,"ty":"sh","ix":36,"ks":{"a":0,"k":{"i":[[0,0],[0,0],[0,0],[0,0]],"o":[[0,0],[0,0],[0,0],[0,0]],"v":[[-144.352,63.805],[-146.535,63.805],[-146.535,52.966],[-144.352,52.966]],"c":true},"ix":2},"nm":"Path 36","mn":"ADBE Vector Shape - Group","hd":false},{"ind":36,"ty":"sh","ix":37,"ks":{"a":0,"k":{"i":[[0,0],[0,0],[0,0],[0,0]],"o":[[0,0],[0,0],[0,0],[0,0]],"v":[[146.536,77.018],[144.353,77.018],[144.353,66.18],[146.536,66.18]],"c":true},"ix":2},"nm":"Path 37","mn":"ADBE Vector Shape - Group","hd":false},{"ind":37,"ty":"sh","ix":38,"ks":{"a":0,"k":{"i":[[0,0],[0,0],[0,0],[0,0]],"o":[[0,0],[0,0],[0,0],[0,0]],"v":[[-144.352,85.484],[-146.535,85.484],[-146.535,74.645],[-144.352,74.645]],"c":true},"ix":2},"nm":"Path 38","mn":"ADBE Vector Shape - Group","hd":false},{"ind":38,"ty":"sh","ix":39,"ks":{"a":0,"k":{"i":[[0,0],[0,0],[0,0],[0,0]],"o":[[0,0],[0,0],[0,0],[0,0]],"v":[[146.536,98.695],[144.353,98.695],[144.353,87.857],[146.536,87.857]],"c":true},"ix":2},"nm":"Path 39","mn":"ADBE Vector Shape - Group","hd":false},{"ind":39,"ty":"sh","ix":40,"ks":{"a":0,"k":{"i":[[0,0],[0,0],[0,0],[0,0]],"o":[[0,0],[0,0],[0,0],[0,0]],"v":[[-144.352,107.161],[-146.535,107.161],[-146.535,96.323],[-144.352,96.323]],"c":true},"ix":2},"nm":"Path 40","mn":"ADBE Vector Shape - Group","hd":false},{"ind":40,"ty":"sh","ix":41,"ks":{"a":0,"k":{"i":[[0,0],[0,0],[0,0],[0,0]],"o":[[0,0],[0,0],[0,0],[0,0]],"v":[[146.536,120.374],[144.353,120.374],[144.353,109.534],[146.536,109.534]],"c":true},"ix":2},"nm":"Path 41","mn":"ADBE Vector Shape - Group","hd":false},{"ind":41,"ty":"sh","ix":42,"ks":{"a":0,"k":{"i":[[0,0],[0,0],[0,0],[0,0]],"o":[[0,0],[0,0],[0,0],[0,0]],"v":[[-144.352,128.84],[-146.535,128.84],[-146.535,118],[-144.352,118]],"c":true},"ix":2},"nm":"Path 42","mn":"ADBE Vector Shape - Group","hd":false},{"ind":42,"ty":"sh","ix":43,"ks":{"a":0,"k":{"i":[[0,0],[0,0],[0,0],[0,0]],"o":[[0,0],[0,0],[0,0],[0,0]],"v":[[146.536,142.051],[144.353,142.051],[144.353,131.212],[146.536,131.212]],"c":true},"ix":2},"nm":"Path 43","mn":"ADBE Vector Shape - Group","hd":false},{"ind":43,"ty":"sh","ix":44,"ks":{"a":0,"k":{"i":[[0,0],[0,0],[0,0],[0,0]],"o":[[0,0],[0,0],[0,0],[0,0]],"v":[[-144.352,150.516],[-146.535,150.516],[-146.535,139.678],[-144.352,139.678]],"c":true},"ix":2},"nm":"Path 44","mn":"ADBE Vector Shape - Group","hd":false},{"ind":44,"ty":"sh","ix":45,"ks":{"a":0,"k":{"i":[[0,0],[0,0],[0,0],[0,0]],"o":[[0,0],[0,0],[0,0],[0,0]],"v":[[146.536,163.728],[144.353,163.728],[144.353,152.89],[146.536,152.89]],"c":true},"ix":2},"nm":"Path 45","mn":"ADBE Vector Shape - Group","hd":false},{"ind":45,"ty":"sh","ix":46,"ks":{"a":0,"k":{"i":[[0,0],[0,0.698],[0,0],[0,0],[0,0],[-0.068,-0.595]],"o":[[-0.078,-0.679],[0,0],[0,0],[0,0],[0,0.615],[0,0]],"v":[[-146.414,172.316],[-146.535,170.25],[-146.535,161.355],[-144.352,161.355],[-144.352,170.25],[-144.249,172.065]],"c":true},"ix":2},"nm":"Path 46","mn":"ADBE Vector Shape - Group","hd":false},{"ind":46,"ty":"sh","ix":47,"ks":{"a":0,"k":{"i":[[3.056,-2.374],[0,0],[-0.862,3.263],[0,0]],"o":[[0,0],[2.681,-2.084],[0,0],[-0.986,3.723]],"v":[[139.683,184.252],[138.344,182.531],[143.838,174.239],[145.948,174.796]],"c":true},"ix":2},"nm":"Path 47","mn":"ADBE Vector Shape - Group","hd":false},{"ind":47,"ty":"sh","ix":48,"ks":{"a":0,"k":{"i":[[0,0],[2.687,2.783],[0,0],[-3.337,-0.509]],"o":[[-3.809,-0.578],[0,0],[2.357,2.442],[0,0]],"v":[[-131.483,187.782],[-141.557,182.568],[-139.99,181.052],[-131.158,185.627]],"c":true},"ix":2},"nm":"Path 48","mn":"ADBE Vector Shape - Group","hd":false},{"ind":48,"ty":"sh","ix":49,"ks":{"a":0,"k":{"i":[[0,0],[0,0],[0,0],[0,0]],"o":[[0,0],[0,0],[0,0],[0,0]],"v":[[-109.654,187.987],[-120.492,187.987],[-120.492,185.803],[-109.654,185.803]],"c":true},"ix":2},"nm":"Path 49","mn":"ADBE Vector Shape - Group","hd":false},{"ind":49,"ty":"sh","ix":50,"ks":{"a":0,"k":{"i":[[0,0],[0,0],[0,0],[0,0]],"o":[[0,0],[0,0],[0,0],[0,0]],"v":[[-87.978,187.987],[-98.815,187.987],[-98.815,185.803],[-87.978,185.803]],"c":true},"ix":2},"nm":"Path 50","mn":"ADBE Vector Shape - Group","hd":false},{"ind":50,"ty":"sh","ix":51,"ks":{"a":0,"k":{"i":[[0,0],[0,0],[0,0],[0,0]],"o":[[0,0],[0,0],[0,0],[0,0]],"v":[[-66.298,187.987],[-77.138,187.987],[-77.138,185.803],[-66.298,185.803]],"c":true},"ix":2},"nm":"Path 51","mn":"ADBE Vector Shape - Group","hd":false},{"ind":51,"ty":"sh","ix":52,"ks":{"a":0,"k":{"i":[[0,0],[0,0],[0,0],[0,0]],"o":[[0,0],[0,0],[0,0],[0,0]],"v":[[-44.621,187.987],[-55.46,187.987],[-55.46,185.803],[-44.621,185.803]],"c":true},"ix":2},"nm":"Path 52","mn":"ADBE Vector Shape - Group","hd":false},{"ind":52,"ty":"sh","ix":53,"ks":{"a":0,"k":{"i":[[0,0],[0,0],[0,0],[0,0]],"o":[[0,0],[0,0],[0,0],[0,0]],"v":[[-22.944,187.987],[-33.783,187.987],[-33.783,185.803],[-22.944,185.803]],"c":true},"ix":2},"nm":"Path 53","mn":"ADBE Vector Shape - Group","hd":false},{"ind":53,"ty":"sh","ix":54,"ks":{"a":0,"k":{"i":[[0,0],[0,0],[0,0],[0,0]],"o":[[0,0],[0,0],[0,0],[0,0]],"v":[[-1.266,187.987],[-12.103,187.987],[-12.103,185.803],[-1.266,185.803]],"c":true},"ix":2},"nm":"Path 54","mn":"ADBE Vector Shape - Group","hd":false},{"ind":54,"ty":"sh","ix":55,"ks":{"a":0,"k":{"i":[[0,0],[0,0],[0,0],[0,0]],"o":[[0,0],[0,0],[0,0],[0,0]],"v":[[20.411,187.987],[9.573,187.987],[9.573,185.803],[20.411,185.803]],"c":true},"ix":2},"nm":"Path 55","mn":"ADBE Vector Shape - Group","hd":false},{"ind":55,"ty":"sh","ix":56,"ks":{"a":0,"k":{"i":[[0,0],[0,0],[0,0],[0,0]],"o":[[0,0],[0,0],[0,0],[0,0]],"v":[[42.089,187.987],[31.25,187.987],[31.25,185.803],[42.089,185.803]],"c":true},"ix":2},"nm":"Path 56","mn":"ADBE Vector Shape - Group","hd":false},{"ind":56,"ty":"sh","ix":57,"ks":{"a":0,"k":{"i":[[0,0],[0,0],[0,0],[0,0]],"o":[[0,0],[0,0],[0,0],[0,0]],"v":[[63.767,187.987],[52.928,187.987],[52.928,185.803],[63.767,185.803]],"c":true},"ix":2},"nm":"Path 57","mn":"ADBE Vector Shape - Group","hd":false},{"ind":57,"ty":"sh","ix":58,"ks":{"a":0,"k":{"i":[[0,0],[0,0],[0,0],[0,0]],"o":[[0,0],[0,0],[0,0],[0,0]],"v":[[85.443,187.987],[74.605,187.987],[74.605,185.803],[85.443,185.803]],"c":true},"ix":2},"nm":"Path 58","mn":"ADBE Vector Shape - Group","hd":false},{"ind":58,"ty":"sh","ix":59,"ks":{"a":0,"k":{"i":[[0,0],[0,0],[0,0],[0,0]],"o":[[0,0],[0,0],[0,0],[0,0]],"v":[[107.122,187.987],[96.282,187.987],[96.282,185.803],[107.122,185.803]],"c":true},"ix":2},"nm":"Path 59","mn":"ADBE Vector Shape - Group","hd":false},{"ind":59,"ty":"sh","ix":60,"ks":{"a":0,"k":{"i":[[0,0],[0,0],[0,0],[0,0]],"o":[[0,0],[0,0],[0,0],[0,0]],"v":[[128.959,187.987],[117.962,187.987],[117.962,185.803],[128.799,185.803]],"c":true},"ix":2},"nm":"Path 60","mn":"ADBE Vector Shape - Group","hd":false},{"ty":"mm","mm":1,"nm":"Merge Paths 1","mn":"ADBE Vector Filter - Merge","hd":false},{"ty":"fl","c":{"a":0,"k":[0.698000021542,0.910000011968,0.791999966491,1],"ix":4},"o":{"a":0,"k":100,"ix":5},"r":1,"bm":0,"nm":"Fill 1","mn":"ADBE Vector Graphic - Fill","hd":false},{"ty":"tr","p":{"a":0,"k":[520.387,217.854],"ix":2},"a":{"a":0,"k":[0,0],"ix":1},"s":{"a":0,"k":[100,100],"ix":3},"r":{"a":0,"k":0,"ix":6},"o":{"a":0,"k":100,"ix":7},"sk":{"a":0,"k":0,"ix":4},"sa":{"a":0,"k":0,"ix":5},"nm":"Transform"}],"nm":"Group 28","np":64,"cix":2,"bm":0,"ix":27,"mn":"ADBE Vector Group","hd":false},{"ty":"gr","it":[{"ind":0,"ty":"sh","ix":1,"ks":{"a":0,"k":{"i":[[9.193,0],[0,0],[0,9.193],[0,0],[-9.193,0],[0,0],[0,-9.192],[0,0]],"o":[[0,0],[-9.193,0],[0,0],[0,-9.192],[0,0],[9.193,0],[0,0],[0,9.193]],"v":[[128.797,186.895],[-128.799,186.895],[-145.444,170.249],[-145.444,-170.25],[-128.799,-186.895],[128.797,-186.895],[145.443,-170.25],[145.443,170.249]],"c":true},"ix":2},"nm":"Path 1","mn":"ADBE Vector Shape - Group","hd":false},{"ty":"fl","c":{"a":0,"k":[0.898000021542,0.969000004787,0.929000016755,1],"ix":4},"o":{"a":0,"k":100,"ix":5},"r":1,"bm":0,"nm":"Fill 1","mn":"ADBE Vector Graphic - Fill","hd":false},{"ty":"tr","p":{"a":0,"k":[520.389,217.855],"ix":2},"a":{"a":0,"k":[0,0],"ix":1},"s":{"a":0,"k":[100,100],"ix":3},"r":{"a":0,"k":0,"ix":6},"o":{"a":0,"k":100,"ix":7},"sk":{"a":0,"k":0,"ix":4},"sa":{"a":0,"k":0,"ix":5},"nm":"Transform"}],"nm":"Group 29","np":4,"cix":2,"bm":0,"ix":28,"mn":"ADBE Vector Group","hd":false},{"ty":"gr","it":[{"ind":0,"ty":"sh","ix":1,"ks":{"a":0,"k":{"i":[[0,0],[0,-78.673],[78.674,0],[0,-19.769],[-19.771,0],[0,0],[0,-19.77],[19.77,0],[0,0],[0,78.674],[-78.673,0],[0,0],[0,19.77],[19.77,0],[0,0],[0,19.77],[-19.77,0]],"o":[[78.674,0],[0,78.674],[-19.771,0],[0,19.77],[0,0],[19.77,0],[0,19.769],[0,0],[-78.673,0],[0,-78.674],[0,0],[19.77,0],[0,-19.77],[0,0],[-19.77,0],[0,-19.769],[0,0]],"v":[[349.527,-214.045],[491.978,-71.594],[349.527,70.858],[313.73,106.654],[349.527,142.451],[461.887,142.451],[497.684,178.248],[461.887,214.045],[-355.232,214.045],[-497.683,71.593],[-355.232,-70.858],[-312.723,-70.858],[-276.927,-106.655],[-312.723,-142.452],[-324.396,-142.452],[-360.193,-178.249],[-324.396,-214.045]],"c":true},"ix":2},"nm":"Path 1","mn":"ADBE Vector Shape - Group","hd":false},{"ty":"fl","c":{"a":0,"k":[0.898000021542,0.969000004787,0.929000016755,1],"ix":4},"o":{"a":0,"k":100,"ix":5},"r":1,"bm":0,"nm":"Fill 1","mn":"ADBE Vector Graphic - Fill","hd":false},{"ty":"tr","p":{"a":0,"k":[497.933,214.295],"ix":2},"a":{"a":0,"k":[0,0],"ix":1},"s":{"a":0,"k":[100,100],"ix":3},"r":{"a":0,"k":0,"ix":6},"o":{"a":0,"k":100,"ix":7},"sk":{"a":0,"k":0,"ix":4},"sa":{"a":0,"k":0,"ix":5},"nm":"Transform"}],"nm":"Group 30","np":4,"cix":2,"bm":0,"ix":29,"mn":"ADBE Vector Group","hd":false}],"ip":0,"op":144,"st":0,"bm":0}],"markers":[]}